rl_blox/__init__.py
rl_blox/algorithm/__init__.py
rl_blox/algorithm/active_mt.py
rl_blox/algorithm/actor_critic.py
rl_blox/algorithm/cmaes.py
rl_blox/algorithm/ddpg.py
rl_blox/algorithm/ddqn.py
rl_blox/algorithm/double_q_learning.py
rl_blox/algorithm/dqn.py
rl_blox/algorithm/dynaq.py
rl_blox/algorithm/monte_carlo.py
rl_blox/algorithm/mrq.py
rl_blox/algorithm/nature_dqn.py
rl_blox/algorithm/pets.py
rl_blox/algorithm/pets_reward_models.py
rl_blox/algorithm/q_learning.py
rl_blox/algorithm/reinforce.py
rl_blox/algorithm/sac.py
rl_blox/algorithm/sarsa.py
rl_blox/algorithm/smt.py
rl_blox/algorithm/td3.py
rl_blox/algorithm/td3_lap.py
rl_blox/algorithm/td7.py
rl_blox/algorithm/uniform_task_sampling.py
rl_blox/blox/__init__.py
rl_blox/blox/checkpointing.py
rl_blox/blox/cross_entropy_method.py
rl_blox/blox/double_qnet.py
rl_blox/blox/losses.py
rl_blox/blox/mapb.py
rl_blox/blox/multitask.py
rl_blox/blox/preprocessing.py
rl_blox/blox/probabilistic_ensemble.py
rl_blox/blox/q_policy.py
rl_blox/blox/replay_buffer.py
rl_blox/blox/return_estimates.py
rl_blox/blox/schedules.py
rl_blox/blox/target_net.py
rl_blox/blox/value_policy.py
rl_blox/blox/embedding/__init__.py
rl_blox/blox/embedding/model_based_encoder.py
rl_blox/blox/embedding/sale.py
rl_blox/blox/embedding/task_embedding.py
rl_blox/blox/function_approximator/__init__.py
rl_blox/blox/function_approximator/gaussian_mlp.py
rl_blox/blox/function_approximator/layer_norm_mlp.py
rl_blox/blox/function_approximator/mlp.py
rl_blox/blox/function_approximator/norm.py
rl_blox/blox/function_approximator/policy_head.py
rl_blox/logging/__init__.py
rl_blox/logging/checkpointer.py
rl_blox/logging/logger.py
rl_blox/logging/plot_stats.py
rl_blox/util/__init__.py
rl_blox/util/error_functions.py
rl_blox/util/experiment_helper.py
rl_blox/util/gymtools.py
rl_blox/util/serialize.py
rl_blox-0.5.4.dist-info/licenses/LICENSE
rl_blox-0.5.4.dist-info/METADATA
rl_blox-0.5.4.dist-info/WHEEL
rl_blox-0.5.4.dist-info/top_level.txt
rl_blox-0.5.4.dist-info/RECORD
