Metadata-Version: 2.4
Name: rl_blox
Version: 0.5.4
Summary: Modular RL building blocks in JAX
Author-email: Melvin Laux <melvin.laux@uni-bremen.de>, Alexander Fabisch <alexander.fabisch@dfki.de>
Maintainer-email: Melvin Laux <melvin.laux@uni-bremen.de>
License-Expression: BSD-3-Clause
Project-URL: Homepage, https://github.com/mlaux1/rl-blox
Project-URL: Issues, https://github.com/mlaux1/rl-blox/issues
Keywords: Reinforcement Learning,RL,JAX
Classifier: Development Status :: 3 - Alpha
Classifier: Programming Language :: Python :: 3
Classifier: Programming Language :: Python :: 3.10
Classifier: Programming Language :: Python :: 3.11
Classifier: Programming Language :: Python :: 3.12
Classifier: Programming Language :: Python :: 3.13
Classifier: Intended Audience :: Science/Research
Classifier: Topic :: Scientific/Engineering :: Artificial Intelligence
Requires-Python: >=3.10
License-File: LICENSE
Requires-Dist: numpy
Requires-Dist: gymnasium>=1.0.0
Requires-Dist: jax>=0.5
Requires-Dist: jaxlib
Requires-Dist: optax
Requires-Dist: tfp-nightly[jax]
Requires-Dist: chex
Requires-Dist: tqdm
Requires-Dist: flax<0.12
Provides-Extra: dev
Requires-Dist: pytest>=6.0; extra == "dev"
Requires-Dist: pre-commit; extra == "dev"
Requires-Dist: flake8; extra == "dev"
Requires-Dist: black; extra == "dev"
Requires-Dist: isort; extra == "dev"
Requires-Dist: pytest-cov; extra == "dev"
Provides-Extra: logging
Requires-Dist: aim; extra == "logging"
Requires-Dist: orbax-checkpoint; extra == "logging"
Provides-Extra: examples
Requires-Dist: gymnasium[classic-control,mujoco,toy-text]; extra == "examples"
Requires-Dist: matplotlib; extra == "examples"
Provides-Extra: doc
Requires-Dist: sphinx; extra == "doc"
Requires-Dist: pydata-sphinx-theme; extra == "doc"
Requires-Dist: numpydoc; extra == "doc"
Provides-Extra: all
Requires-Dist: rl_blox[dev,doc,examples,logging]; extra == "all"
Dynamic: license-file
